helloworld/__init__.py
helloworld/helloworld.py
helloworld_daniel_package-0.0.1.dist-info/METADATA
helloworld_daniel_package-0.0.1.dist-info/WHEEL
helloworld_daniel_package-0.0.1.dist-info/top_level.txt
helloworld_daniel_package-0.0.1.dist-info/RECORD
