Metadata-Version: 2.1
Name: helloworld-daniel-package
Version: 0.0.1
Summary: modelo de pacote python
Home-page: https://github.com/DanielNery/modelo_pacote-python
Author: daniel_nery
Author-email: danielpontesnery@gmail.com
License: UNKNOWN
Platform: UNKNOWN
Requires-Python: >=3.8
